polls/__init__.py
polls/admin.py
polls/apps.py
polls/models.py
polls/tests.py
polls/urls.py
polls/views.py
polls/migrations/0001_initial.py
polls/migrations/__init__.py
polls/static/polls/style.css
polls/static/polls/images/background.gif
polls/templates/polls/detail.html
polls/templates/polls/index.html
polls/templates/polls/results.html
pandadjango_polls-1.2.0.dist-info/License.md
pandadjango_polls-1.2.0.dist-info/METADATA
pandadjango_polls-1.2.0.dist-info/WHEEL
pandadjango_polls-1.2.0.dist-info/top_level.txt
pandadjango_polls-1.2.0.dist-info/RECORD
