Metadata-Version: 2.1
Name: pandadjango-polls
Version: 1.2.0
Summary: A simple Django app to conduct Web-based polls.
Home-page: https://github.com/pypa/sampleproject
Author: zoupan
Author-email: 463471132@qq.com
License: BSD License
Platform: UNKNOWN
Classifier: Environment :: Web Environment
Classifier: Framework :: Django
Classifier: Intended Audience :: Developers
Classifier: License :: OSI Approved :: BSD License
Classifier: Operating System :: OS Independent
Classifier: Programming Language :: Python
Classifier: Programming Language :: Python :: 3.5
Classifier: Programming Language :: Python :: 3.6
Classifier: Topic :: Internet :: WWW/HTTP
Classifier: Topic :: Internet :: WWW/HTTP :: Dynamic Content
